certbot_dns_hostingnl/__init__.py
certbot_dns_hostingnl/dns_hostingnl.py
certbot_dns_hostingnl-0.1.5.dist-info/LICENSE
certbot_dns_hostingnl-0.1.5.dist-info/METADATA
certbot_dns_hostingnl-0.1.5.dist-info/WHEEL
certbot_dns_hostingnl-0.1.5.dist-info/entry_points.txt
certbot_dns_hostingnl-0.1.5.dist-info/top_level.txt
certbot_dns_hostingnl-0.1.5.dist-info/RECORD
