Metadata-Version: 2.1
Name: certbot-dns-hostingnl
Version: 0.1.5
Summary: Hosting.nl DNS Authenticator plugin for Certbot
Home-page: https://github.com/TECH7Fox/certbot-dns-hostingnl
License: MIT
License-File: LICENSE
Requires-Dist: certbot
